kronoterm_cloud_api/__init__.py
kronoterm_cloud_api/client.py
kronoterm_cloud_api/kronoterm_enums.py
kronoterm_cloud_api-0.1.17.dist-info/licenses/LICENSE
kronoterm_cloud_api-0.1.17.dist-info/METADATA
kronoterm_cloud_api-0.1.17.dist-info/WHEEL
kronoterm_cloud_api-0.1.17.dist-info/top_level.txt
kronoterm_cloud_api-0.1.17.dist-info/RECORD
