Metadata-Version: 2.4
Name: kronoterm-cloud-api
Version: 0.1.17
Summary: API for Kronoterm heat pumps cloud
Author-email: Matevž <matevzlesko@gmail.com>
License-Expression: GPL-3.0-or-later
Project-URL: Homepage, https://github.com/LeskoIam/kronoterm_cloud_api
Project-URL: Issues, https://github.com/LeskoIam/kronoterm_cloud_api/issues
Classifier: Development Status :: 2 - Pre-Alpha
Classifier: Programming Language :: Python :: 3
Classifier: Operating System :: OS Independent
Requires-Python: >=3.8
License-File: LICENSE
Requires-Dist: requests>=2.32.3
Requires-Dist: python-dotenv>=1.0.1
Dynamic: license-file
